jinja_i18n_tools/__init__.py
jinja_i18n_tools/__main__.py
jinja_i18n_tools/babel.cfg
jinja_i18n_tools/cli.py
jinja_i18n_tools/i18n_auto.py
jinja_i18n_tools/i18n_compile.py
jinja_i18n_tools/i18n_translations.py
jinja_i18n_tools/utils.py
jinja_i18n_tools-0.1.2.dist-info/licenses/LICENSE
jinja_i18n_tools-0.1.2.dist-info/METADATA
jinja_i18n_tools-0.1.2.dist-info/WHEEL
jinja_i18n_tools-0.1.2.dist-info/entry_points.txt
jinja_i18n_tools-0.1.2.dist-info/top_level.txt
jinja_i18n_tools-0.1.2.dist-info/RECORD
