Metadata-Version: 2.4
Name: jinja-i18n-tools
Version: 0.1.2
Summary: Automated i18n tool for Jinja2 projects using Babel and Google Translate
Author-email: Tamer OnLine <info@tameronline.com>
License: MIT
Keywords: jinja2,i18n,babel,translation,cli,localization
Requires-Python: >=3.12
License-File: LICENSE
Requires-Dist: jinja2>=3.1.0
Requires-Dist: babel>=2.9.1
Requires-Dist: deep-translator>=1.11.4
Requires-Dist: polib>=1.1.1
Dynamic: license-file
